Workbook

Sheet Overview
A1: OPBOH™ 37 Stages / Work Packages
A2: Full-Cycle Stage-Gate Architecture | Controlled Master Register | Version 1.1
A3: From Strategic Inception to Sustainable Impact, Performance Monitoring and Future Expansion
A5: 37 Stages / work packages | C5: 222 Controlled focus fields | E5: 3,700 Stage-gate questions | G5: 100 Questions per stage
A9: Full-cycle control logic
A10: Each work package is a controlled assurance unit. It has a defined purpose, six primary focus fields, 100 evidence-based questions, accountable roles, entry and exit conditions, decision risks, mandatory outputs and a documented progression recommendation. No stage progresses on elapsed time or a tick-box response alone.
A14: Lifecycle Cluster | B14: Stages | C14: Questions | D14: Focus Fields | F14: Control Test | G14: Required | H14: Result
A15: Opportunity, Mandate and Site Control | B15: =COUNTIF('37 Stage Register'!$D$5:$D$41,A15) -> 5 | C15: =SUMIF('37 Stage Register'!$D$5:$D$41,A15,'37 Stage Register'!$L$5:$L$41) -> 500 | D15: =SUMIF('37 Stage Register'!$D$5:$D$41,A15,'37 Stage Register'!$M$5:$M$41) -> 30 | F15: Stage count | G15: 37 | H15: =COUNTA('37 Stage Register'!$A$5:$A$41) -> 37
A16: Feasibility, Rights, Approvals and Stakeholders | B16: =COUNTIF('37 Stage Register'!$D$5:$D$41,A16) -> 7 | C16: =SUMIF('37 Stage Register'!$D$5:$D$41,A16,'37 Stage Register'!$L$5:$L$41) -> 700 | D16: =SUMIF('37 Stage Register'!$D$5:$D$41,A16,'37 Stage Register'!$M$5:$M$41) -> 42 | F16: Question count | G16: 3700 | H16: =COUNTA('3,700 Question Index'!$A$5:$A$3704) -> 3700
A17: Concept, Commercial Alignment and Occupier Strategy | B17: =COUNTIF('37 Stage Register'!$D$5:$D$41,A17) -> 7 | C17: =SUMIF('37 Stage Register'!$D$5:$D$41,A17,'37 Stage Register'!$L$5:$L$41) -> 700 | D17: =SUMIF('37 Stage Register'!$D$5:$D$41,A17,'37 Stage Register'!$M$5:$M$41) -> 42 | F17: Focus field count | G17: 222 | H17: =COUNTA('222 Focus Fields'!$A$5:$A$226) -> 222
A18: Design, Cost, Capital, Procurement and Permitting | B18: =COUNTIF('37 Stage Register'!$D$5:$D$41,A18) -> 7 | C18: =SUMIF('37 Stage Register'!$D$5:$D$41,A18,'37 Stage Register'!$L$5:$L$41) -> 700 | D18: =SUMIF('37 Stage Register'!$D$5:$D$41,A18,'37 Stage Register'!$M$5:$M$41) -> 42 | F18: Stages with 100 questions | G18: 37 | H18: =COUNTIF('37 Stage Register'!$L$5:$L$41,100) -> 37
A19: Construction, Quality, Commissioning and Handover | B19: =COUNTIF('37 Stage Register'!$D$5:$D$41,A19) -> 7 | C19: =SUMIF('37 Stage Register'!$D$5:$D$41,A19,'37 Stage Register'!$L$5:$L$41) -> 700 | D19: =SUMIF('37 Stage Register'!$D$5:$D$41,A19,'37 Stage Register'!$M$5:$M$41) -> 42
A20: Operations, Maintenance, Impact and Expansion | B20: =COUNTIF('37 Stage Register'!$D$5:$D$41,A20) -> 4 | C20: =SUMIF('37 Stage Register'!$D$5:$D$41,A20,'37 Stage Register'!$L$5:$L$41) -> 400 | D20: =SUMIF('37 Stage Register'!$D$5:$D$41,A20,'37 Stage Register'!$M$5:$M$41) -> 24
A22: Evidence rule: Yes/No/N/A and a 0–5 score are assessment inputs; progression requires accepted, current, complete, signed where applicable and traceable evidence, reviewed under delegated authority.

Sheet 37 Stage Register
A1: OPBOH™ 37-Stage / Work-Package Master Register
A2: Complete lifecycle identity, focus, dependencies, accountabilities and coverage controls
A4: Stage | B4: WP Code | C4: Stage / Work Package | D4: Lifecycle Cluster | E4: Primary Focus | F4: Stage Purpose | G4: Predecessor | H4: Successor | I4: Accountable Roles | J4: Principal Decision Risk | K4: Decision Options | L4: Questions | M4: Focus Fields
A5: 01 | B5: WP01 | C5: Strategic Inception and Project Mandate | D5: Opportunity, Mandate and Site Control | E5: Project vision, scope mandate, decision authority, developer appointment, client objectives, governance structure | F5: Establish, assess and evidence project vision, scope mandate, decision authority, developer appointment, client objectives, governance structure before authorising progression beyond strategic inception and project mandate. | G5: Opportunity intake / mandate initiation | H5: WP02 | I5: Project Sponsor; OPBOH Lead Assessor; Legal/Governance Lead; Project Manager | J5: Unclear mandate, ownership, authority or site control may invalidate later commitments and expenditure. | K5: Proceed / Proceed with conditions / Remediate and reassess / Hold / Rework / Stop or restructure | L5: 100 | M5: 6
A6: 02 | B6: WP02 | C6: Site Identification and Opportunity Discovery | D6: Opportunity, Mandate and Site Control | E6: R567 exposure, 3 ha site extent, market gap, community catchment, mobility flows, competitive landscape | F6: Establish, assess and evidence r567 exposure, 3 ha site extent, market gap, community catchment, mobility flows, competitive landscape before authorising progression beyond site identification and opportunity discovery. | G6: WP01 | H6: WP03 | I6: Project Sponsor; OPBOH Lead Assessor; Legal/Governance Lead; Project Manager | J6: Unclear mandate, ownership, authority or site control may invalidate later commitments and expenditure. | K6: Proceed / Proceed with conditions / Remediate and reassess / Hold / Rework / Stop or restructure | L6: 100 | M6: 6
A7: 03 | B7: WP03 | C7: Preliminary Site Screening | D7: Opportunity, Mandate and Site Control | E7: Ownership confirmation, servitudes, basic zoning position, environmental sensitivity, access constraints, bulk services proximity | F7: Establish, assess and evidence ownership confirmation, servitudes, basic zoning position, environmental sensitivity, access constraints, bulk services proximity before authorising progression beyond preliminary site screening. | G7: WP02 | H7: WP04 | I7: Project Sponsor; OPBOH Lead Assessor; Legal/Governance Lead; Project Manager | J7: Unclear mandate, ownership, authority or site control may invalidate later commitments and expenditure. | K7: Proceed / Proceed with conditions / Remediate and reassess / Hold / Rework / Stop or restructure | L7: 100 | M7: 6
A8: 04 | B8: WP04 | C8: Sponsor and Entity Readiness | D8: Opportunity, Mandate and Site Control | E8: Client capacity, corporate documentation, tax status, decision-making mandate, funding preparedness, legal authority | F8: Establish, assess and evidence client capacity, corporate documentation, tax status, decision-making mandate, funding preparedness, legal authority before authorising progression beyond sponsor and entity readiness. | G8: WP03 | H8: WP05 | I8: Project Sponsor; OPBOH Lead Assessor; Legal/Governance Lead; Project Manager | J8: Unclear mandate, ownership, authority or site control may invalidate later commitments and expenditure. | K8: Proceed / Proceed with conditions / Remediate and reassess / Hold / Rework / Stop or restructure | L8: 100 | M8: 6
A9: 05 | B9: WP05 | C9: Land Security and Site Control | D9: Opportunity, Mandate and Site Control | E9: Title deed, landowner consent, lease or purchase rights, site boundaries, SG diagram, wayleaves | F9: Establish, assess and evidence title deed, landowner consent, lease or purchase rights, site boundaries, sg diagram, wayleaves before authorising progression beyond land security and site control. | G9: WP04 | H9: WP06 | I9: Project Sponsor; OPBOH Lead Assessor; Legal/Governance Lead; Project Manager | J9: Unclear mandate, ownership, authority or site control may invalidate later commitments and expenditure. | K9: Proceed / Proceed with conditions / Remediate and reassess / Hold / Rework / Stop or restructure | L9: 100 | M9: 6
A10: 06 | B10: WP06 | C10: Feasibility Studies and Market Demand | D10: Feasibility, Rights, Approvals and Stakeholders | E10: Retail demand, fuel demand, Boxer anchor viability, line-shop demand, fast-food demand, traffic volumes | F10: Establish, assess and evidence retail demand, fuel demand, boxer anchor viability, line-shop demand, fast-food demand, traffic volumes before authorising progression beyond feasibility studies and market demand. | G10: WP05 | H10: WP07 | I10: Project Manager; Planning/Environmental/Engineering Specialists; Relevant Authorities; OPBOH Assessor | J10: Unresolved feasibility, access, services, environmental, zoning or stakeholder constraints may make the project non-viable or delay approvals. | K10: Proceed / Proceed with conditions / Remediate and reassess / Hold / Rework / Stop or restructure | L10: 100 | M10: 6
A11: 07 | B11: WP07 | C11: Traffic, Access and Mobility Feasibility | D11: Feasibility, Rights, Approvals and Stakeholders | E11: R567 entrance, turning lanes, sight distances, heavy vehicle movement, pedestrian safety, public transport interface | F11: Establish, assess and evidence r567 entrance, turning lanes, sight distances, heavy vehicle movement, pedestrian safety, public transport interface before authorising progression beyond traffic, access and mobility feasibility. | G11: WP06 | H11: WP08 | I11: Project Manager; Planning/Environmental/Engineering Specialists; Relevant Authorities; OPBOH Assessor | J11: Unresolved feasibility, access, services, environmental, zoning or stakeholder constraints may make the project non-viable or delay approvals. | K11: Proceed / Proceed with conditions / Remediate and reassess / Hold / Rework / Stop or restructure | L11: 100 | M11: 6
A12: 08 | B12: WP08 | C12: Bulk Services and Infrastructure Feasibility | D12: Feasibility, Rights, Approvals and Stakeholders | E12: Water supply, sewer capacity, stormwater discharge, electrical capacity, fire water, ICT services | F12: Establish, assess and evidence water supply, sewer capacity, stormwater discharge, electrical capacity, fire water, ict services before authorising progression beyond bulk services and infrastructure feasibility. | G12: WP07 | H12: WP09 | I12: Project Manager; Planning/Environmental/Engineering Specialists; Relevant Authorities; OPBOH Assessor | J12: Unresolved feasibility, access, services, environmental, zoning or stakeholder constraints may make the project non-viable or delay approvals. | K12: Proceed / Proceed with conditions / Remediate and reassess / Hold / Rework / Stop or restructure | L12: 100 | M12: 6
A13: 09 | B13: WP09 | C13: Environmental Screening and Scoping | D13: Feasibility, Rights, Approvals and Stakeholders | E13: NEMA triggers, wetland sensitivity, biodiversity risk, heritage risk, groundwater risk, noise sources | F13: Establish, assess and evidence nema triggers, wetland sensitivity, biodiversity risk, heritage risk, groundwater risk, noise sources before authorising progression beyond environmental screening and scoping. | G13: WP08 | H13: WP10 | I13: Project Manager; Planning/Environmental/Engineering Specialists; Relevant Authorities; OPBOH Assessor | J13: Unresolved feasibility, access, services, environmental, zoning or stakeholder constraints may make the project non-viable or delay approvals. | K13: Proceed / Proceed with conditions / Remediate and reassess / Hold / Rework / Stop or restructure | L13: 100 | M13: 6
A14: 10 | B14: WP10 | C14: Land Use Rights and Zoning | D14: Feasibility, Rights, Approvals and Stakeholders | E14: Current agricultural zoning, rezoning pathway, consent use, site development plan, parking compliance, FAR and coverage | F14: Establish, assess and evidence current agricultural zoning, rezoning pathway, consent use, site development plan, parking compliance, far and coverage before authorising progression beyond land use rights and zoning. | G14: WP09 | H14: WP11 | I14: Project Manager; Planning/Environmental/Engineering Specialists; Relevant Authorities; OPBOH Assessor | J14: Unresolved feasibility, access, services, environmental, zoning or stakeholder constraints may make the project non-viable or delay approvals. | K14: Proceed / Proceed with conditions / Remediate and reassess / Hold / Rework / Stop or restructure | L14: 100 | M14: 6
A15: 11 | B15: WP11 | C15: Environmental Authorisation - Estimated 10 Months | D15: Feasibility, Rights, Approvals and Stakeholders | E15: Screening report, specialist studies, draft BAR or EIA, public participation, authority comments, empr | F15: Establish, assess and evidence screening report, specialist studies, draft bar or eia, public participation, authority comments, empr before authorising progression beyond environmental authorisation - estimated 10 months. | G15: WP10 | H15: WP12 | I15: Project Manager; Planning/Environmental/Engineering Specialists; Relevant Authorities; OPBOH Assessor | J15: Unresolved feasibility, access, services, environmental, zoning or stakeholder constraints may make the project non-viable or delay approvals. | K15: Proceed / Proceed with conditions / Remediate and reassess / Hold / Rework / Stop or restructure | L15: 100 | M15: 6
A16: 12 | B16: WP12 | C16: Stakeholder Mapping and Public Participation | D16: Feasibility, Rights, Approvals and Stakeholders | E16: Municipality, road authority, DMRE, environmental authority, community leaders, neighbouring landowners | F16: Establish, assess and evidence municipality, road authority, dmre, environmental authority, community leaders, neighbouring landowners before authorising progression beyond stakeholder mapping and public participation. | G16: WP11 | H16: WP13 | I16: Project Manager; Planning/Environmental/Engineering Specialists; Relevant Authorities; OPBOH Assessor | J16: Unresolved feasibility, access, services, environmental, zoning or stakeholder constraints may make the project non-viable or delay approvals. | K16: Proceed / Proceed with conditions / Remediate and reassess / Hold / Rework / Stop or restructure | L16: 100 | M16: 6
... A41: 37 | B41: WP37 | C41: Sustainable Impact, Performance Monitoring and Future Expansion | D41: Operations, Maintenance, Impact and Expansion | E41: ESG reporting, job creation, local procurement, community benefit, energy efficiency, water performance | F41: Establish, assess and evidence esg reporting, job creation, local procurement, community benefit, energy efficiency, water performance before authorising progression beyond sustainable impact, performance monitoring and future expansion. | G41: WP36 | H41: Operations and impact-continuity assurance | I41: Asset/Property Manager; Operators/Tenants; Maintenance Lead; ESG/MERL Lead; Owner Governance | J41: Weak operating, maintenance or impact controls may erode functionality, financial sustainability, compliance and long-term benefits. | K41: Proceed / Proceed with conditions / Remediate and reassess / Hold / Rework / Stop or restructure | L41: 100 | M41: 6

Sheet 222 Focus Fields
A1: OPBOH™ 222 Controlled Stage Focus Fields
A2: Six explicit focus fields mapped to every one of the 37 work packages
A4: Field Code | B4: Stage | C4: WP Code | D4: Stage / Work Package | E4: Focus Field | F4: Data Type / Allowed Values | G4: Req. | H4: Validation and Assurance Use | I4: Lifecycle Cluster | J4: Source Status
A5: WP01-01 | B5: 01 | C5: WP01 | D5: Strategic Inception and Project Mandate | E5: Project Vision | F5: Structured value + evidence + status | G5: M/C | H5: Captures the controlled project vision data for Stage 01 (Strategic Inception and Project Mandate); link source, owner, status, evidence, risk and decision impact. | I5: Opportunity, Mandate and Site Control | J5: Controlled v1.1
A6: WP01-02 | B6: 01 | C6: WP01 | D6: Strategic Inception and Project Mandate | E6: Scope Mandate | F6: Structured value + evidence + status | G6: M/C | H6: Captures the controlled scope mandate data for Stage 01 (Strategic Inception and Project Mandate); link source, owner, status, evidence, risk and decision impact. | I6: Opportunity, Mandate and Site Control | J6: Controlled v1.1
A7: WP01-03 | B7: 01 | C7: WP01 | D7: Strategic Inception and Project Mandate | E7: Decision Authority | F7: Linked party / engagement / due-diligence status | G7: M/C | H7: Captures the controlled decision authority data for Stage 01 (Strategic Inception and Project Mandate); link source, owner, status, evidence, risk and decision impact. | I7: Opportunity, Mandate and Site Control | J7: Controlled v1.1
A8: WP01-04 | B8: 01 | C8: WP01 | D8: Strategic Inception and Project Mandate | E8: Developer Appointment | F8: Structured value + evidence + status | G8: M/C | H8: Captures the controlled developer appointment data for Stage 01 (Strategic Inception and Project Mandate); link source, owner, status, evidence, risk and decision impact. | I8: Opportunity, Mandate and Site Control | J8: Controlled v1.1
A9: WP01-05 | B9: 01 | C9: WP01 | D9: Strategic Inception and Project Mandate | E9: Client Objectives | F9: Structured value + evidence + status | G9: M/C | H9: Captures the controlled client objectives data for Stage 01 (Strategic Inception and Project Mandate); link source, owner, status, evidence, risk and decision impact. | I9: Opportunity, Mandate and Site Control | J9: Controlled v1.1
A10: WP01-06 | B10: 01 | C10: WP01 | D10: Strategic Inception and Project Mandate | E10: Governance Structure | F10: Structured value + evidence + status | G10: M/C | H10: Captures the controlled governance structure data for Stage 01 (Strategic Inception and Project Mandate); link source, owner, status, evidence, risk and decision impact. | I10: Opportunity, Mandate and Site Control | J10: Controlled v1.1
A11: WP02-01 | B11: 02 | C11: WP02 | D11: Site Identification and Opportunity Discovery | E11: R567 Exposure | F11: Structured value + evidence + status | G11: M/C | H11: Captures the controlled r567 exposure data for Stage 02 (Site Identification and Opportunity Discovery); link source, owner, status, evidence, risk and decision impact. | I11: Opportunity, Mandate and Site Control | J11: Controlled v1.1
A12: WP02-02 | B12: 02 | C12: WP02 | D12: Site Identification and Opportunity Discovery | E12: 3 Ha Site Extent | F12: Numeric / percentage / currency with unit and period | G12: M/C | H12: Captures the controlled 3 ha site extent data for Stage 02 (Site Identification and Opportunity Discovery); link source, owner, status, evidence, risk and decision impact. | I12: Opportunity, Mandate and Site Control | J12: Controlled v1.1
A13: WP02-03 | B13: 02 | C13: WP02 | D13: Site Identification and Opportunity Discovery | E13: Market Gap | F13: Structured value + evidence + status | G13: M/C | H13: Captures the controlled market gap data for Stage 02 (Site Identification and Opportunity Discovery); link source, owner, status, evidence, risk and decision impact. | I13: Opportunity, Mandate and Site Control | J13: Controlled v1.1
A14: WP02-04 | B14: 02 | C14: WP02 | D14: Site Identification and Opportunity Discovery | E14: Community Catchment | F14: Structured value + evidence + status | G14: M/C | H14: Captures the controlled community catchment data for Stage 02 (Site Identification and Opportunity Discovery); link source, owner, status, evidence, risk and decision impact. | I14: Opportunity, Mandate and Site Control | J14: Controlled v1.1
A15: WP02-05 | B15: 02 | C15: WP02 | D15: Site Identification and Opportunity Discovery | E15: Mobility Flows | F15: Structured value + evidence + status | G15: M/C | H15: Captures the controlled mobility flows data for Stage 02 (Site Identification and Opportunity Discovery); link source, owner, status, evidence, risk and decision impact. | I15: Opportunity, Mandate and Site Control | J15: Controlled v1.1
... A226: WP37-06 | B226: 37 | C226: WP37 | D226: Sustainable Impact, Performance Monitoring and Future Expansion | E226: Water Performance | F226: Numeric / percentage / currency with unit and period | G226: M/C | H226: Captures the controlled water performance data for Stage 37 (Sustainable Impact, Performance Monitoring and Future Expansion); link source, owner, status, evidence, risk and decision impact. | I226: Operations, Maintenance, Impact and Expansion | J226: Controlled v1.1

Sheet Stage Control Matrix
A1: OPBOH™ Stage Assurance Control Matrix
A2: Operational entry, exit, evidence, risk, output and progression controls for each work package
A4: Stage | B4: WP Code | C4: Stage / Work Package | D4: Entry Condition | E4: Top Evidence Patterns | F4: Top Reference Bases | G4: Exit Condition | H4: Mandatory Outputs | I4: Responsible Roles | J4: Decision Risk | K4: Decision Options | L4: Control Status
A5: 01 | B5: WP01 | C5: Strategic Inception and Project Mandate | D5: Prior work-package outputs accepted or formally waived; mandate, owner and applicable evidence request confirmed. | E5: Signed memo, checklist, source document and responsible-person confirmation. | Register entry, supporting drawing/report, approval note and updated risk item. | Professional/specialist note, meeting minute, correspondence and decision record. | Updated schedule, cost note, assumption log and evidence index reference. | Authority response, compliance checklist, file note and management approval. | F5: King IV governance practice; Companies Act 71 of 2008; project mandate file | PMBOK stage-gate governance; board resolution; delegated authority matrix | ISO 31000 risk management; stakeholder decision register; project charter | G5: Applicable questions completed; required evidence accepted; critical failures resolved or escalated; decision and conditions approved by the delegated authority. | H5: Approved Strategic Inception and Project Mandate assessment record; evidence index; findings and risk update; corrective-action/condition register; signed progression recommendation. | I5: Project Sponsor; OPBOH Lead Assessor; Legal/Governance Lead; Project Manager | J5: Unclear mandate, ownership, authority or site control may invalidate later commitments and expenditure. | K5: Proceed / Proceed with conditions / Remediate and reassess / Hold / Rework / Stop or restructure | L5: Controlled
A6: 02 | B6: WP02 | C6: Site Identification and Opportunity Discovery | D6: Prior work-package outputs accepted or formally waived; mandate, owner and applicable evidence request confirmed. | E6: Signed memo, checklist, source document and responsible-person confirmation. | Register entry, supporting drawing/report, approval note and updated risk item. | Professional/specialist note, meeting minute, correspondence and decision record. | Updated schedule, cost note, assumption log and evidence index reference. | Authority response, compliance checklist, file note and management approval. | F6: SPLUMA Act 16 of 2013; municipal land use scheme; title deed/SG diagram | Deeds Registries Act 47 of 1937; Surveyor-General records; servitude register | Municipal Planning By-law; wayleave requirements; landowner consent | G6: Applicable questions completed; required evidence accepted; critical failures resolved or escalated; decision and conditions approved by the delegated authority. | H6: Approved Site Identification and Opportunity Discovery assessment record; evidence index; findings and risk update; corrective-action/condition register; signed progression recommendation. | I6: Project Sponsor; OPBOH Lead Assessor; Legal/Governance Lead; Project Manager | J6: Unclear mandate, ownership, authority or site control may invalidate later commitments and expenditure. | K6: Proceed / Proceed with conditions / Remediate and reassess / Hold / Rework / Stop or restructure | L6: Controlled
A7: 03 | B7: WP03 | C7: Preliminary Site Screening | D7: Prior work-package outputs accepted or formally waived; mandate, owner and applicable evidence request confirmed. | E7: Signed memo, checklist, source document and responsible-person confirmation. | Register entry, supporting drawing/report, approval note and updated risk item. | Professional/specialist note, meeting minute, correspondence and decision record. | Updated schedule, cost note, assumption log and evidence index reference. | Authority response, compliance checklist, file note and management approval. | F7: SPLUMA Act 16 of 2013; municipal land use scheme; title deed/SG diagram | Deeds Registries Act 47 of 1937; Surveyor-General records; servitude register | Municipal Planning By-law; wayleave requirements; landowner consent | G7: Applicable questions completed; required evidence accepted; critical failures resolved or escalated; decision and conditions approved by the delegated authority. | H7: Approved Preliminary Site Screening assessment record; evidence index; findings and risk update; corrective-action/condition register; signed progression recommendation. | I7: Project Sponsor; OPBOH Lead Assessor; Legal/Governance Lead; Project Manager | J7: Unclear mandate, ownership, authority or site control may invalidate later commitments and expenditure. | K7: Proceed / Proceed with conditions / Remediate and reassess / Hold / Rework / Stop or restructure | L7: Controlled
A8: 04 | B8: WP04 | C8: Sponsor and Entity Readiness | D8: Prior work-package outputs accepted or formally waived; mandate, owner and applicable evidence request confirmed. | E8: Signed memo, checklist, source document and responsible-person confirmation. | Register entry, supporting drawing/report, approval note and updated risk item. | Professional/specialist note, meeting minute, correspondence and decision record. | Updated schedule, cost note, assumption log and evidence index reference. | Authority response, compliance checklist, file note and management approval. | F8: King IV governance practice; Companies Act 71 of 2008; project mandate file | PMBOK stage-gate governance; board resolution; delegated authority matrix | ISO 31000 risk management; stakeholder decision register; project charter | G8: Applicable questions completed; required evidence accepted; critical failures resolved or escalated; decision and conditions approved by the delegated authority. | H8: Approved Sponsor and Entity Readiness assessment record; evidence index; findings and risk update; corrective-action/condition register; signed progression recommendation. | I8: Project Sponsor; OPBOH Lead Assessor; Legal/Governance Lead; Project Manager | J8: Unclear mandate, ownership, authority or site control may invalidate later commitments and expenditure. | K8: Proceed / Proceed with conditions / Remediate and reassess / Hold / Rework / Stop or restructure | L8: Controlled
A9: 05 | B9: WP05 | C9: Land Security and Site Control | D9: Prior work-package outputs accepted or formally waived; mandate, owner and applicable evidence request confirmed. | E9: Signed memo, checklist, source document and responsible-person confirmation. | Register entry, supporting drawing/report, approval note and updated risk item. | Professional/specialist note, meeting minute, correspondence and decision record. | Updated schedule, cost note, assumption log and evidence index reference. | Authority response, compliance checklist, file note and management approval. | F9: SPLUMA Act 16 of 2013; municipal land use scheme; title deed/SG diagram | Deeds Registries Act 47 of 1937; Surveyor-General records; servitude register | Municipal Planning By-law; wayleave requirements; landowner consent | G9: Applicable questions completed; required evidence accepted; critical failures resolved or escalated; decision and conditions approved by the delegated authority. | H9: Approved Land Security and Site Control assessment record; evidence index; findings and risk update; corrective-action/condition register; signed progression recommendation. | I9: Project Sponsor; OPBOH Lead Assessor; Legal/Governance Lead; Project Manager | J9: Unclear mandate, ownership, authority or site control may invalidate later commitments and expenditure. | K9: Proceed / Proceed with conditions / Remediate and reassess / Hold / Rework / Stop or restructure | L9: Controlled
A10: 06 | B10: WP06 | C10: Feasibility Studies and Market Demand | D10: Prior work-package outputs accepted or formally waived; mandate, owner and applicable evidence request confirmed. | E10: Signed memo, checklist, source document and responsible-person confirmation. | Register entry, supporting drawing/report, approval note and updated risk item. | Professional/specialist note, meeting minute, correspondence and decision record. | Updated schedule, cost note, assumption log and evidence index reference. | Authority response, compliance checklist, file note and management approval. | F10: IFRS/IFRS for SMEs principles; lender due diligence checklist; signed financial model | CIDB/procurement best practice; cost plan; QS measurement and BOQ controls | Treasury-style value-for-money principles; funding term sheet; drawdown controls | G10: Applicable questions completed; required evidence accepted; critical failures resolved or escalated; decision and conditions approved by the delegated authority. | H10: Approved Feasibility Studies and Market Demand assessment record; evidence index; findings and risk update; corrective-action/condition register; signed progression recommendation. | I10: Project Manager; Planning/Environmental/Engineering Specialists; Relevant Authorities; OPBOH Assessor | J10: Unresolved feasibility, access, services, environmental, zoning or stakeholder constraints may make the project non-viable or delay approvals. | K10: Proceed / Proceed with conditions / Remediate and reassess / Hold / Rework / Stop or restructure | L10: Controlled
A11: 07 | B11: WP07 | C11: Traffic, Access and Mobility Feasibility | D11: Prior work-package outputs accepted or formally waived; mandate, owner and applicable evidence request confirmed. | E11: Signed memo, checklist, source document and responsible-person confirmation. | Register entry, supporting drawing/report, approval note and updated risk item. | Professional/specialist note, meeting minute, correspondence and decision record. | Updated schedule, cost note, assumption log and evidence index reference. | Authority response, compliance checklist, file note and management approval. | F11: SANRAL/road authority access requirements; TMH/TRH road design guidance | Municipal roads and stormwater standards; traffic impact assessment | SANS 10400-S access; pedestrian safety and universal access principles | G11: Applicable questions completed; required evidence accepted; critical failures resolved or escalated; decision and conditions approved by the delegated authority. | H11: Approved Traffic, Access and Mobility Feasibility assessment record; evidence index; findings and risk update; corrective-action/condition register; signed progression recommendation. | I11: Project Manager; Planning/Environmental/Engineering Specialists; Relevant Authorities; OPBOH Assessor | J11: Unresolved feasibility, access, services, environmental, zoning or stakeholder constraints may make the project non-viable or delay approvals. | K11: Proceed / Proceed with conditions / Remediate and reassess / Hold / Rework / Stop or restructure | L11: Controlled
A12: 08 | B12: WP08 | C12: Bulk Services and Infrastructure Feasibility | D12: Prior work-package outputs accepted or formally waived; mandate, owner and applicable evidence request confirmed. | E12: Signed memo, checklist, source document and responsible-person confirmation. | Register entry, supporting drawing/report, approval note and updated risk item. | Professional/specialist note, meeting minute, correspondence and decision record. | Updated schedule, cost note, assumption log and evidence index reference. | Authority response, compliance checklist, file note and management approval. | F12: National Building Regulations and Building Standards Act 103 of 1977; SANS 10400 | SANS 10252 water; SANS 10400 fire, access and drainage; professional design certificates | SANS/municipal engineering standards; approved SDP; rational fire design | G12: Applicable questions completed; required evidence accepted; critical failures resolved or escalated; decision and conditions approved by the delegated authority. | H12: Approved Bulk Services and Infrastructure Feasibility assessment record; evidence index; findings and risk update; corrective-action/condition register; signed progression recommendation. | I12: Project Manager; Planning/Environmental/Engineering Specialists; Relevant Authorities; OPBOH Assessor | J12: Unresolved feasibility, access, services, environmental, zoning or stakeholder constraints may make the project non-viable or delay approvals. | K12: Proceed / Proceed with conditions / Remediate and reassess / Hold / Rework / Stop or restructure | L12: Controlled
A13: 09 | B13: WP09 | C13: Environmental Screening and Scoping | D13: Prior work-package outputs accepted or formally waived; mandate, owner and applicable evidence request confirmed. | E13: Signed memo, checklist, source document and responsible-person confirmation. | Register entry, supporting drawing/report, approval note and updated risk item. | Professional/specialist note, meeting minute, correspondence and decision record. | Updated schedule, cost note, assumption log and evidence index reference. | Authority response, compliance checklist, file note and management approval. | F13: NEMA Act 107 of 1998; EIA Regulations, 2014; DFFE screening requirements | National Water Act 36 of 1998; biodiversity and wetland specialist guidance | NHRA Act 25 of 1999; public participation record; EMPr controls | G13: Applicable questions completed; required evidence accepted; critical failures resolved or escalated; decision and conditions approved by the delegated authority. | H13: Approved Environmental Screening and Scoping assessment record; evidence index; findings and risk update; corrective-action/condition register; signed progression recommendation. | I13: Project Manager; Planning/Environmental/Engineering Specialists; Relevant Authorities; OPBOH Assessor | J13: Unresolved feasibility, access, services, environmental, zoning or stakeholder constraints may make the project non-viable or delay approvals. | K13: Proceed / Proceed with conditions / Remediate and reassess / Hold / Rework / Stop or restructure | L13: Controlled
A14: 10 | B14: WP10 | C14: Land Use Rights and Zoning | D14: Prior work-package outputs accepted or formally waived; mandate, owner and applicable evidence request confirmed. | E14: Signed memo, checklist, source document and responsible-person confirmation. | Register entry, supporting drawing/report, approval note and updated risk item. | Professional/specialist note, meeting minute, correspondence and decision record. | Updated schedule, cost note, assumption log and evidence index reference. | Authority response, compliance checklist, file note and management approval. | F14: SPLUMA Act 16 of 2013; municipal land use scheme; title deed/SG diagram | Deeds Registries Act 47 of 1937; Surveyor-General records; servitude register | Municipal Planning By-law; wayleave requirements; landowner consent | G14: Applicable questions completed; required evidence accepted; critical failures resolved or escalated; decision and conditions approved by the delegated authority. | H14: Approved Land Use Rights and Zoning assessment record; evidence index; findings and risk update; corrective-action/condition register; signed progression recommendation. | I14: Project Manager; Planning/Environmental/Engineering Specialists; Relevant Authorities; OPBOH Assessor | J14: Unresolved feasibility, access, services, environmental, zoning or stakeholder constraints may make the project non-viable or delay approvals. | K14: Proceed / Proceed with conditions / Remediate and reassess / Hold / Rework / Stop or restructure | L14: Controlled
A15: 11 | B15: WP11 | C15: Environmental Authorisation - Estimated 10 Months | D15: Prior work-package outputs accepted or formally waived; mandate, owner and applicable evidence request confirmed. | E15: Signed memo, checklist, source document and responsible-person confirmation. | Register entry, supporting drawing/report, approval note and updated risk item. | Professional/specialist note, meeting minute, correspondence and decision record. | Updated schedule, cost note, assumption log and evidence index reference. | Authority response, compliance checklist, file note and management approval. | F15: NEMA Act 107 of 1998; EIA Regulations, 2014; DFFE screening requirements | National Water Act 36 of 1998; biodiversity and wetland specialist guidance | NHRA Act 25 of 1999; public participation record; EMPr controls | G15: Applicable questions completed; required evidence accepted; critical failures resolved or escalated; decision and conditions approved by the delegated authority. | H15: Approved Environmental Authorisation - Estimated 10 Months assessment record; evidence index; findings and risk update; corrective-action/condition register; signed progression recommendation. | I15: Project Manager; Planning/Environmental/Engineering Specialists; Relevant Authorities; OPBOH Assessor | J15: Unresolved feasibility, access, services, environmental, zoning or stakeholder constraints may make the project non-viable or delay approvals. | K15: Proceed / Proceed with conditions / Remediate and reassess / Hold / Rework / Stop or restructure | L15: Controlled
... A41: 37 | B41: WP37 | C41: Sustainable Impact, Performance Monitoring and Future Expansion | D41: Prior work-package outputs accepted or formally waived; mandate, owner and applicable evidence request confirmed. | E41: Signed memo, checklist, source document and responsible-person confirmation. | Register entry, supporting drawing/report, approval note and updated risk item. | Professional/specialist note, meeting minute, correspondence and decision record. | Updated schedule, cost note, assumption log and evidence index reference. | Authority response, compliance checklist, file note and management approval. | F41: ESG reporting practice; local economic development commitments; utility performance data | ISO 14001 environmental management principles; water and energy monitoring | Socio-economic impact reporting; community benefit register; future expansion plan | G41: Applicable questions completed; required evidence accepted; critical failures resolved or escalated; decision and conditions approved by the delegated authority. | H41: Approved Sustainable Impact, Performance Monitoring and Future Expansion assessment record; evidence index; findings and risk update; corrective-action/condition register; signed progression recommendation. | I41: Asset/Property Manager; Operators/Tenants; Maintenance Lead; ESG/MERL Lead; Owner Governance | J41: Weak operating, maintenance or impact controls may erode functionality, financial sustainability, compliance and long-term benefits. | K41: Proceed / Proceed with conditions / Remediate and reassess / Hold / Rework / Stop or restructure | L41: Controlled

Sheet 3,700 Question Index
A1: OPBOH™ 3,700 Stage-Gate Question Index
A2: Source questions mapped to the 37 controlled stages; assessment-response columns are ready for implementation
A4: Question No. | B4: Stage | C4: WP Code | D4: Stage / Work Package | E4: Strategic Stage-Gate Question | F4: Evidence Required | G4: Reference Basis | H4: Assessment Control
A5: 01.001 | B5: 01 | C5: WP01 | D5: Strategic Inception and Project Mandate | E5: Has the project team confirmed project vision - governance approval in a current, signed and traceable evidence file? | F5: Signed memo, checklist, source document and responsible-person confirmation. | G5: King IV governance practice; Companies Act 71 of 2008; project mandate file | H5: Yes / No / N/A + Score 0–5 + Rating
A6: 01.002 | B6: 01 | C6: WP01 | D6: Strategic Inception and Project Mandate | E6: Is there a responsible owner, due date and approval route for scope mandate - governance approval? | F6: Register entry, supporting drawing/report, approval note and updated risk item. | G6: PMBOK stage-gate governance; board resolution; delegated authority matrix | H6: Yes / No / N/A + Score 0–5 + Rating
A7: 01.003 | B7: 01 | C7: WP01 | D7: Strategic Inception and Project Mandate | E7: Has the gate file tested whether decision authority - governance approval creates a material risk to Bahlaloga Riverside Complex? | F7: Professional/specialist note, meeting minute, correspondence and decision record. | G7: ISO 31000 risk management; stakeholder decision register; project charter | H7: Yes / No / N/A + Score 0–5 + Rating
A8: 01.004 | B8: 01 | C8: WP01 | D8: Strategic Inception and Project Mandate | E8: Are assumptions for developer appointment - governance approval documented, current and supported by source evidence? | F8: Updated schedule, cost note, assumption log and evidence index reference. | G8: King IV governance practice; Companies Act 71 of 2008; project mandate file | H8: Yes / No / N/A + Score 0–5 + Rating
A9: 01.005 | B9: 01 | C9: WP01 | D9: Strategic Inception and Project Mandate | E9: Has the relevant authority, specialist or professional adviser reviewed client objectives - governance approval where required? | F9: Authority response, compliance checklist, file note and management approval. | G9: PMBOK stage-gate governance; board resolution; delegated authority matrix | H9: Yes / No / N/A + Score 0–5 + Rating
A10: 01.006 | B10: 01 | C10: WP01 | D10: Strategic Inception and Project Mandate | E10: Is the decision record for governance structure - governance approval aligned with the approved project mandate and scope? | F10: Due-diligence record, gap analysis, mitigation action and close-out proof. | G10: ISO 31000 risk management; stakeholder decision register; project charter | H10: Yes / No / N/A + Score 0–5 + Rating
A11: 01.007 | B11: 01 | C11: WP01 | D11: Strategic Inception and Project Mandate | E11: Have cost, programme and compliance implications of project vision - legal authority been captured in the risk register? | F11: Reviewed report, annotated plan, gate pack extract and approval signature. | G11: King IV governance practice; Companies Act 71 of 2008; project mandate file | H11: Yes / No / N/A + Score 0–5 + Rating
A12: 01.008 | B12: 01 | C12: WP01 | D12: Strategic Inception and Project Mandate | E12: Has the team obtained written confirmation or documented proof for scope mandate - legal authority? | F12: Current certificate/letter/report, version control and document-control entry. | G12: PMBOK stage-gate governance; board resolution; delegated authority matrix | H12: Yes / No / N/A + Score 0–5 + Rating
A13: 01.009 | B13: 01 | C13: WP01 | D13: Strategic Inception and Project Mandate | E13: Does the evidence for decision authority - legal authority support a clear proceed, hold, revise or stop gate decision? | F13: Inspection/test record, issue log, corrective action and close-out evidence. | G13: ISO 31000 risk management; stakeholder decision register; project charter | H13: Yes / No / N/A + Score 0–5 + Rating
A14: 01.010 | B14: 01 | C14: WP01 | D14: Strategic Inception and Project Mandate | E14: Have dependencies linked to developer appointment - legal authority been identified before moving to the next stage? | F14: Tenant/operator/funder/authority confirmation and gate-approval recommendation. | G14: King IV governance practice; Companies Act 71 of 2008; project mandate file | H14: Yes / No / N/A + Score 0–5 + Rating
A15: 01.011 | B15: 01 | C15: WP01 | D15: Strategic Inception and Project Mandate | E15: Has the project team confirmed client objectives - legal authority in a current, signed and traceable evidence file? | F15: Signed memo, checklist, source document and responsible-person confirmation. | G15: PMBOK stage-gate governance; board resolution; delegated authority matrix | H15: Yes / No / N/A + Score 0–5 + Rating
... A3704: 37.100 | B3704: 37 | C3704: WP37 | D3704: Sustainable Impact, Performance Monitoring and Future Expansion | E3704: Have dependencies linked to community benefit - stakeholder acceptance been identified before moving to the next stage? | F3704: Tenant/operator/funder/authority confirmation and gate-approval recommendation. | G3704: ESG reporting practice; local economic development commitments; utility performance data | H3704: Yes / No / N/A + Score 0–5 + Rating

Sheet Evidence & References
A1: Evidence and Reference Coverage by Stage
A2: Most recurrent evidence patterns and reference bases extracted from each stage's 100 source questions
A4: Stage | B4: WP Code | C4: Stage / Work Package | D4: Evidence Pattern 1 | E4: Evidence Pattern 2 | F4: Evidence Pattern 3 | G4: Primary Reference Basis | H4: Coverage
A5: 01 | B5: WP01 | C5: Strategic Inception and Project Mandate | D5: Signed memo, checklist, source document and responsible-person confirmation. | E5: Register entry, supporting drawing/report, approval note and updated risk item. | F5: Professional/specialist note, meeting minute, correspondence and decision record. | G5: King IV governance practice; Companies Act 71 of 2008; project mandate file | H5: 100 questions / 6 focus fields
A6: 02 | B6: WP02 | C6: Site Identification and Opportunity Discovery | D6: Signed memo, checklist, source document and responsible-person confirmation. | E6: Register entry, supporting drawing/report, approval note and updated risk item. | F6: Professional/specialist note, meeting minute, correspondence and decision record. | G6: SPLUMA Act 16 of 2013; municipal land use scheme; title deed/SG diagram | H6: 100 questions / 6 focus fields
A7: 03 | B7: WP03 | C7: Preliminary Site Screening | D7: Signed memo, checklist, source document and responsible-person confirmation. | E7: Register entry, supporting drawing/report, approval note and updated risk item. | F7: Professional/specialist note, meeting minute, correspondence and decision record. | G7: SPLUMA Act 16 of 2013; municipal land use scheme; title deed/SG diagram | H7: 100 questions / 6 focus fields
A8: 04 | B8: WP04 | C8: Sponsor and Entity Readiness | D8: Signed memo, checklist, source document and responsible-person confirmation. | E8: Register entry, supporting drawing/report, approval note and updated risk item. | F8: Professional/specialist note, meeting minute, correspondence and decision record. | G8: King IV governance practice; Companies Act 71 of 2008; project mandate file | H8: 100 questions / 6 focus fields
A9: 05 | B9: WP05 | C9: Land Security and Site Control | D9: Signed memo, checklist, source document and responsible-person confirmation. | E9: Register entry, supporting drawing/report, approval note and updated risk item. | F9: Professional/specialist note, meeting minute, correspondence and decision record. | G9: SPLUMA Act 16 of 2013; municipal land use scheme; title deed/SG diagram | H9: 100 questions / 6 focus fields
A10: 06 | B10: WP06 | C10: Feasibility Studies and Market Demand | D10: Signed memo, checklist, source document and responsible-person confirmation. | E10: Register entry, supporting drawing/report, approval note and updated risk item. | F10: Professional/specialist note, meeting minute, correspondence and decision record. | G10: IFRS/IFRS for SMEs principles; lender due diligence checklist; signed financial model | H10: 100 questions / 6 focus fields
A11: 07 | B11: WP07 | C11: Traffic, Access and Mobility Feasibility | D11: Signed memo, checklist, source document and responsible-person confirmation. | E11: Register entry, supporting drawing/report, approval note and updated risk item. | F11: Professional/specialist note, meeting minute, correspondence and decision record. | G11: SANRAL/road authority access requirements; TMH/TRH road design guidance | H11: 100 questions / 6 focus fields
A12: 08 | B12: WP08 | C12: Bulk Services and Infrastructure Feasibility | D12: Signed memo, checklist, source document and responsible-person confirmation. | E12: Register entry, supporting drawing/report, approval note and updated risk item. | F12: Professional/specialist note, meeting minute, correspondence and decision record. | G12: National Building Regulations and Building Standards Act 103 of 1977; SANS 10400 | H12: 100 questions / 6 focus fields
A13: 09 | B13: WP09 | C13: Environmental Screening and Scoping | D13: Signed memo, checklist, source document and responsible-person confirmation. | E13: Register entry, supporting drawing/report, approval note and updated risk item. | F13: Professional/specialist note, meeting minute, correspondence and decision record. | G13: NEMA Act 107 of 1998; EIA Regulations, 2014; DFFE screening requirements | H13: 100 questions / 6 focus fields
A14: 10 | B14: WP10 | C14: Land Use Rights and Zoning | D14: Signed memo, checklist, source document and responsible-person confirmation. | E14: Register entry, supporting drawing/report, approval note and updated risk item. | F14: Professional/specialist note, meeting minute, correspondence and decision record. | G14: SPLUMA Act 16 of 2013; municipal land use scheme; title deed/SG diagram | H14: 100 questions / 6 focus fields
A15: 11 | B15: WP11 | C15: Environmental Authorisation - Estimated 10 Months | D15: Signed memo, checklist, source document and responsible-person confirmation. | E15: Register entry, supporting drawing/report, approval note and updated risk item. | F15: Professional/specialist note, meeting minute, correspondence and decision record. | G15: NEMA Act 107 of 1998; EIA Regulations, 2014; DFFE screening requirements | H15: 100 questions / 6 focus fields
... A41: 37 | B41: WP37 | C41: Sustainable Impact, Performance Monitoring and Future Expansion | D41: Signed memo, checklist, source document and responsible-person confirmation. | E41: Register entry, supporting drawing/report, approval note and updated risk item. | F41: Professional/specialist note, meeting minute, correspondence and decision record. | G41: ESG reporting practice; local economic development commitments; utility performance data | H41: 100 questions / 6 focus fields

Sheet Source & Control
A1: Source, Authority and Control
A2: Controlled provenance of the OPBOH 37-stage/work-package architecture
A4: Control Attribute | B4: Controlled Value
A5: Framework | B5: OPBOH™ — Organisational and Project Bill of Health
A6: Module | B6: Full-Cycle Assessment Module
A7: Version | B7: 1.1
A8: Stages / Work Packages | B8: 37
A9: Questions | B9: 3700
A10: Controlled Focus Fields | B10: 222
A11: Stage Source | B11: Bahlaloga_Riverside_Complex_3700_Stage_Gate_Questions_Bank_ FV 2216.docx
A12: Field Source | B12: OPBOH_Full_Cycle_Assessment_Module_Field_Requirements_v1.1.docx
A13: Assessment Inputs | B13: Yes / No / N/A; Score 0–5; rating
A14: Classification | B14: Confidential and Proprietary
A15: Owner | B15: IPAC Governance Systems (Pty) Ltd
A17: Control Principle | B17: Controlled Statement
A18: A date, percentage or tick does not authorise progression. Gate approval depends on accepted, current, complete, signed where applicable and traceable evidence, linked to the responsible owner and reviewed by the correct delegated authority. Critical failures are non-averageable and unresolved conditions must remain visible in the progression decision.
A24: Register Scope | B24: Controlled Statement
A25: This workbook operationalises the 37 sequential project stages/work packages, their 222 controlled focus fields and the 3,700 source stage-gate questions. Lifecycle-cluster labels, purpose statements, role summaries, decision-risk summaries and entry/exit formulations are implementation-oriented register views derived from the controlled stage names, primary focus areas and evidence architecture; they do not replace framework-owner approval or specialist judgement.
