Workbook

Sheet Overview
A1: OPBOH™ 827 Explicit Module Fields
A2: Full-Cycle Assessment Module | Controlled Master Register | Version 1.1
A3: End-to-End Governance. Evidence-Based Decisions. Assured Outcomes.
A5: 827 Explicit module fields | C5: 37 Controlled work packages | E5: 3,700 Source assessment questions | G5: v1.1 Controlled specification
A9: Workbook purpose
A10: This workbook operationalises the complete 827-field data dictionary defined by IPACGS-OPBOH-MOD-FLD-001. It provides one filterable register for system configuration, assessment design, evidence control, scoring, workflow, stage-gate decisions, delivery assurance, operations and impact continuity.
A14: Required Indicator | B14: Meaning | C14: Register Count | D14: % of Fields | F14: Control | G14: Status | H14: Result
A15: M | B15: Mandatory | C15: =COUNTIF('827 Field Register'!$I$5:$I$831,A15) -> 386 | D15: =C15/827 -> 0.46674728 | F15: Field count | G15: Must equal 827 | H15: =COUNTA('827 Field Register'!$G$5:$G$831) -> 827
A16: M/C | B16: Mandatory when applicability rule is true | C16: =COUNTIF('827 Field Register'!$I$5:$I$831,A16) -> 232 | D16: =C16/827 -> 0.28053204 | F16: Unique field codes | G16: Validated during controlled build | H16: =COUNTA('827 Field Register'!$G$5:$G$831) -> 827
A17: C | B17: Conditional | C17: =COUNTIF('827 Field Register'!$I$5:$I$831,A17) -> 197 | D17: =C17/827 -> 0.2382104 | F17: Work packages | G17: Must equal 37 | H17: =COUNTA('37 Work Packages'!$A$5:$A$41) -> 37
A18: O | B18: Optional/supporting | C18: =COUNTIF('827 Field Register'!$I$5:$I$831,A18) -> 0 | D18: =C18/827 -> 0 | F18: Blank field codes | G18: Must equal 0 | H18: =COUNTBLANK('827 Field Register'!$G$5:$G$831) -> 0
A20: Controlled principle: A date, percentage or tick does not authorise progression. Accepted, current and traceable evidence, reviewed by the correct authority, is required before a gate decision may be issued.

Sheet 827 Field Register
A1: OPBOH™ Controlled Field Register
A2: 827 unique explicit fields extracted from the approved v1.1 field-requirements specification
A3: Filter by section, module family, work package, requirement or field code. Field meanings below preserve the controlled source wording.
A4: No. | B4: Section | C4: Section Title | D4: Module Family | E4: WP Code | F4: Work Package | G4: Field Code | H4: Field Name | I4: Req. | J4: Data Type / Allowed Values | K4: Validation and Assurance Use
A5: 1 | B5: 5 | C5: Universal Record, Version and Control Metadata | D5: Universal Record, Version and Control Metadata | G5: GEN-001 | H5: Global record ID | I5: M | J5: UUID / immutable identifier | K5: Unique across the platform; required for traceability and reconciliation.
A6: 2 | B6: 5 | C6: Universal Record, Version and Control Metadata | D6: Universal Record, Version and Control Metadata | G6: GEN-002 | H6: Tenant / portfolio ID | I6: M | J6: Linked identifier | K6: Separates organisation and portfolio records and supports controlled reporting.
A7: 3 | B7: 5 | C7: Universal Record, Version and Control Metadata | D7: Universal Record, Version and Control Metadata | G7: GEN-003 | H7: Project ID | I7: M | J7: Linked identifier | K7: Joins the record to the authoritative master project record.
A8: 4 | B8: 5 | C8: Universal Record, Version and Control Metadata | D8: Universal Record, Version and Control Metadata | G8: GEN-004 | H8: Record type | I8: M | J8: Controlled list | K8: Identifies question, response, evidence, risk, action, decision, asset, indicator or other object.
A9: 5 | B9: 5 | C9: Universal Record, Version and Control Metadata | D9: Universal Record, Version and Control Metadata | G9: GEN-005 | H9: Record title | I9: M | J9: Text 1-250 characters | K9: Human-readable label used in search, registers and reports.
A10: 6 | B10: 5 | C10: Universal Record, Version and Control Metadata | D10: Universal Record, Version and Control Metadata | G10: GEN-006 | H10: Record description | I10: C | J10: Long text | K10: Defines the content and prevents ambiguous interpretation.
A11: 7 | B11: 5 | C11: Universal Record, Version and Control Metadata | D11: Universal Record, Version and Control Metadata | G11: GEN-007 | H11: Record status | I11: M | J11: Draft / Active / Under Review / Accepted / Rejected / Withdrawn / Superseded / Archived | K11: Controls workflow eligibility and use in assurance decisions.
A12: 8 | B12: 5 | C12: Universal Record, Version and Control Metadata | D12: Universal Record, Version and Control Metadata | G12: GEN-008 | H12: Record owner | I12: M | J12: Linked person / role | K12: Establishes accountability for accuracy, maintenance and closure.
A13: 9 | B13: 5 | C13: Universal Record, Version and Control Metadata | D13: Universal Record, Version and Control Metadata | G13: GEN-009 | H13: Business data steward | I13: C | J13: Linked person / role | K13: Identifies the person responsible for data quality and source reconciliation.
A14: 10 | B14: 5 | C14: Universal Record, Version and Control Metadata | D14: Universal Record, Version and Control Metadata | G14: GEN-010 | H14: Source system / origin | I14: M | J14: Controlled list + reference | K14: Distinguishes primary evidence, imported data, assessor entry and generated data.
A15: 11 | B15: 5 | C15: Universal Record, Version and Control Metadata | D15: Universal Record, Version and Control Metadata | G15: GEN-011 | H15: Source reference | I15: M | J15: Text / URI / register number | K15: Provides traceability to the originating document, register or external system.
A16: 12 | B16: 5 | C16: Universal Record, Version and Control Metadata | D16: Universal Record, Version and Control Metadata | G16: GEN-012 | H16: Effective-from date | I16: M | J16: Date-time | K16: Determines when the record becomes valid for assessment use.
... A609: 605 | B609: 25 | C609: Reusable Fields for Every Stage / Work Package | D609: Reusable Fields for Every Stage / Work Package | G609: STC-015 | H609: Stage reassessment trigger | I609: M | J609: Expiry / change / incident / dependency | K609: Supports continuous assurance.
A610: 606 | B610: 26 | C610: WP01 - Strategic Inception and Project Mandate | D610: Stage-Specific Work-Package Fields | E610: WP01 | F610: Strategic Inception and Project Mandate | G610: WP01-01 | H610: Project Vision | I610: M/C | J610: Structured value + evidence + status | K610: Captures the controlled project vision data for Stage 01 (Strategic Inception and Project Mandate); link source, owner, status, evidence, risk and decision impact.
A611: 607 | B611: 26 | C611: WP01 - Strategic Inception and Project Mandate | D611: Stage-Specific Work-Package Fields | E611: WP01 | F611: Strategic Inception and Project Mandate | G611: WP01-02 | H611: Scope Mandate | I611: M/C | J611: Structured value + evidence + status | K611: Captures the controlled scope mandate data for Stage 01 (Strategic Inception and Project Mandate); link source, owner, status, evidence, risk and decision impact.
A612: 608 | B612: 26 | C612: WP01 - Strategic Inception and Project Mandate | D612: Stage-Specific Work-Package Fields | E612: WP01 | F612: Strategic Inception and Project Mandate | G612: WP01-03 | H612: Decision Authority | I612: M/C | J612: Linked party / engagement / due-diligence status | K612: Captures the controlled decision authority data for Stage 01 (Strategic Inception and Project Mandate); link source, owner, status, evidence, risk and decision impact.
A613: 609 | B613: 26 | C613: WP01 - Strategic Inception and Project Mandate | D613: Stage-Specific Work-Package Fields | E613: WP01 | F613: Strategic Inception and Project Mandate | G613: WP01-04 | H613: Developer Appointment | I613: M/C | J613: Structured value + evidence + status | K613: Captures the controlled developer appointment data for Stage 01 (Strategic Inception and Project Mandate); link source, owner, status, evidence, risk and decision impact.
A614: 610 | B614: 26 | C614: WP01 - Strategic Inception and Project Mandate | D614: Stage-Specific Work-Package Fields | E614: WP01 | F614: Strategic Inception and Project Mandate | G614: WP01-05 | H614: Client Objectives | I614: M/C | J614: Structured value + evidence + status | K614: Captures the controlled client objectives data for Stage 01 (Strategic Inception and Project Mandate); link source, owner, status, evidence, risk and decision impact.
A615: 611 | B615: 26 | C615: WP01 - Strategic Inception and Project Mandate | D615: Stage-Specific Work-Package Fields | E615: WP01 | F615: Strategic Inception and Project Mandate | G615: WP01-06 | H615: Governance Structure | I615: M/C | J615: Structured value + evidence + status | K615: Captures the controlled governance structure data for Stage 01 (Strategic Inception and Project Mandate); link source, owner, status, evidence, risk and decision impact.
A616: 612 | B616: 26 | C616: WP02 - Site Identification and Opportunity Discovery | D616: Stage-Specific Work-Package Fields | E616: WP02 | F616: Site Identification and Opportunity Discovery | G616: WP02-01 | H616: R567 Exposure | I616: M/C | J616: Structured value + evidence + status | K616: Captures the controlled r567 exposure data for Stage 02 (Site Identification and Opportunity Discovery); link source, owner, status, evidence, risk and decision impact.
A617: 613 | B617: 26 | C617: WP02 - Site Identification and Opportunity Discovery | D617: Stage-Specific Work-Package Fields | E617: WP02 | F617: Site Identification and Opportunity Discovery | G617: WP02-02 | H617: 3 Ha Site Extent | I617: M/C | J617: Numeric / percentage / currency with unit and period | K617: Captures the controlled 3 ha site extent data for Stage 02 (Site Identification and Opportunity Discovery); link source, owner, status, evidence, risk and decision impact.
A618: 614 | B618: 26 | C618: WP02 - Site Identification and Opportunity Discovery | D618: Stage-Specific Work-Package Fields | E618: WP02 | F618: Site Identification and Opportunity Discovery | G618: WP02-03 | H618: Market Gap | I618: M/C | J618: Structured value + evidence + status | K618: Captures the controlled market gap data for Stage 02 (Site Identification and Opportunity Discovery); link source, owner, status, evidence, risk and decision impact.
A619: 615 | B619: 26 | C619: WP02 - Site Identification and Opportunity Discovery | D619: Stage-Specific Work-Package Fields | E619: WP02 | F619: Site Identification and Opportunity Discovery | G619: WP02-04 | H619: Community Catchment | I619: M/C | J619: Structured value + evidence + status | K619: Captures the controlled community catchment data for Stage 02 (Site Identification and Opportunity Discovery); link source, owner, status, evidence, risk and decision impact.
A620: 616 | B620: 26 | C620: WP02 - Site Identification and Opportunity Discovery | D620: Stage-Specific Work-Package Fields | E620: WP02 | F620: Site Identification and Opportunity Discovery | G620: WP02-05 | H620: Mobility Flows | I620: M/C | J620: Structured value + evidence + status | K620: Captures the controlled mobility flows data for Stage 02 (Site Identification and Opportunity Discovery); link source, owner, status, evidence, risk and decision impact.
A621: 617 | B621: 26 | C621: WP02 - Site Identification and Opportunity Discovery | D621: Stage-Specific Work-Package Fields | E621: WP02 | F621: Site Identification and Opportunity Discovery | G621: WP02-06 | H621: Competitive Landscape | I621: M/C | J621: Structured value + evidence + status | K621: Captures the controlled competitive landscape data for Stage 02 (Site Identification and Opportunity Discovery); link source, owner, status, evidence, risk and decision impact.
... A831: 827 | B831: 26 | C831: WP37 - Sustainable Impact, Performance Monitoring and Future Expansion | D831: Stage-Specific Work-Package Fields | E831: WP37 | F831: Sustainable Impact, Performance Monitoring and Future Expansion | G831: WP37-06 | H831: Water Performance | I831: M/C | J831: Numeric / percentage / currency with unit and period | K831: Captures the controlled water performance data for Stage 37 (Sustainable Impact, Performance Monitoring and Future Expansion); link source, owner, status, evidence, risk and decision impact.

Sheet Section Summary
A1: OPBOH™ Section Allocation
A2: Field counts reconcile directly to the controlled 827-field register
A4: Section | B4: Section Title | C4: Module Type | D4: Field Count | E4: % of 827 | F4: First Field Code
A5: 5 | B5: Universal Record, Version and Control Metadata | C5: Core / reusable | D5: =COUNTIFS('827 Field Register'!$B$5:$B$831,A5,'827 Field Register'!$C$5:$C$831,B5) -> 25 | E5: =D5/827 -> 0.030229746 | F5: =INDEX('827 Field Register'!$G$5:$G$831,MATCH(1,('827 Field Register'!$B$5:$B$831=A5)*('827 Field Register'!$C$5:$C$831=B5),0)) -> #N/A
A6: 6 | B6: Opportunity, Project and Portfolio Master Data | C6: Core / reusable | D6: =COUNTIFS('827 Field Register'!$B$5:$B$831,A6,'827 Field Register'!$C$5:$C$831,B6) -> 25 | E6: =D6/827 -> 0.030229746 | F6: =INDEX('827 Field Register'!$G$5:$G$831,MATCH(1,('827 Field Register'!$B$5:$B$831=A6)*('827 Field Register'!$C$5:$C$831=B6),0)) -> #N/A
A7: 7 | B7: Organisation, Sponsor, Ownership and Governance | C7: Core / reusable | D7: =COUNTIFS('827 Field Register'!$B$5:$B$831,A7,'827 Field Register'!$C$5:$C$831,B7) -> 23 | E7: =D7/827 -> 0.027811366 | F7: =INDEX('827 Field Register'!$G$5:$G$831,MATCH(1,('827 Field Register'!$B$5:$B$831=A7)*('827 Field Register'!$C$5:$C$831=B7),0)) -> #N/A
A8: 8 | B8: Site, Land, Property and Location Control | C8: Core / reusable | D8: =COUNTIFS('827 Field Register'!$B$5:$B$831,A8,'827 Field Register'!$C$5:$C$831,B8) -> 22 | E8: =D8/827 -> 0.026602177 | F8: =INDEX('827 Field Register'!$G$5:$G$831,MATCH(1,('827 Field Register'!$B$5:$B$831=A8)*('827 Field Register'!$C$5:$C$831=B8),0)) -> #N/A
A9: 9 | B9: Stakeholder, Authority and Public-Participation Data | C9: Core / reusable | D9: =COUNTIFS('827 Field Register'!$B$5:$B$831,A9,'827 Field Register'!$C$5:$C$831,B9) -> 19 | E9: =D9/827 -> 0.022974607 | F9: =INDEX('827 Field Register'!$G$5:$G$831,MATCH(1,('827 Field Register'!$B$5:$B$831=A9)*('827 Field Register'!$C$5:$C$831=B9),0)) -> #N/A
A10: 10 | B10: OPBOH Question and Control Catalogue Configuration | C10: Core / reusable | D10: =COUNTIFS('827 Field Register'!$B$5:$B$831,A10,'827 Field Register'!$C$5:$C$831,B10) -> 30 | E10: =D10/827 -> 0.036275695 | F10: =INDEX('827 Field Register'!$G$5:$G$831,MATCH(1,('827 Field Register'!$B$5:$B$831=A10)*('827 Field Register'!$C$5:$C$831=B10),0)) -> #N/A
A11: 11 | B11: Assessment Instance, Response and Reviewer Record | C11: Core / reusable | D11: =COUNTIFS('827 Field Register'!$B$5:$B$831,A11,'827 Field Register'!$C$5:$C$831,B11) -> 33 | E11: =D11/827 -> 0.039903265 | F11: =INDEX('827 Field Register'!$G$5:$G$831,MATCH(1,('827 Field Register'!$B$5:$B$831=A11)*('827 Field Register'!$C$5:$C$831=B11),0)) -> #N/A
A12: 12 | B12: Evidence and Document-Control Register | C12: Core / reusable | D12: =COUNTIFS('827 Field Register'!$B$5:$B$831,A12,'827 Field Register'!$C$5:$C$831,B12) -> 94 | E12: =D12/827 -> 0.11366385 | F12: =INDEX('827 Field Register'!$G$5:$G$831,MATCH(1,('827 Field Register'!$B$5:$B$831=A12)*('827 Field Register'!$C$5:$C$831=B12),0)) -> #N/A
A13: 13 | B13: Scoring, RAG, Readiness and Assurance Opinion | C13: Core / reusable | D13: =COUNTIFS('827 Field Register'!$B$5:$B$831,A13,'827 Field Register'!$C$5:$C$831,B13) -> 26 | E13: =D13/827 -> 0.031438936 | F13: =INDEX('827 Field Register'!$G$5:$G$831,MATCH(1,('827 Field Register'!$B$5:$B$831=A13)*('827 Field Register'!$C$5:$C$831=B13),0)) -> #N/A
A14: 14 | B14: Risk, Issue, Finding, Control, Action and Condition | C14: Core / reusable | D14: =COUNTIFS('827 Field Register'!$B$5:$B$831,A14,'827 Field Register'!$C$5:$C$831,B14) -> 30 | E14: =D14/827 -> 0.036275695 | F14: =INDEX('827 Field Register'!$G$5:$G$831,MATCH(1,('827 Field Register'!$B$5:$B$831=A14)*('827 Field Register'!$C$5:$C$831=B14),0)) -> #N/A
A15: 15 | B15: Lifecycle, Work-Package, Schedule and Gate Control | C15: Core / reusable | D15: =COUNTIFS('827 Field Register'!$B$5:$B$831,A15,'827 Field Register'!$C$5:$C$831,B15) -> 24 | E15: =D15/827 -> 0.029020556 | F15: =INDEX('827 Field Register'!$G$5:$G$831,MATCH(1,('827 Field Register'!$B$5:$B$831=A15)*('827 Field Register'!$C$5:$C$831=B15),0)) -> #N/A
A16: 16 | B16: Financial, Commercial, Funding and Capital Data | C16: Core / reusable | D16: =COUNTIFS('827 Field Register'!$B$5:$B$831,A16,'827 Field Register'!$C$5:$C$831,B16) -> 29 | E16: =D16/827 -> 0.035066505 | F16: =INDEX('827 Field Register'!$G$5:$G$831,MATCH(1,('827 Field Register'!$B$5:$B$831=A16)*('827 Field Register'!$C$5:$C$831=B16),0)) -> #N/A
... A62: 26 | B62: WP37 - Sustainable Impact, Performance Monitoring and Future Expansion | C62: Stage-specific | D62: =COUNTIFS('827 Field Register'!$B$5:$B$831,A62,'827 Field Register'!$C$5:$C$831,B62) -> 6 | E62: =D62/827 -> 0.0072551391 | F62: =INDEX('827 Field Register'!$G$5:$G$831,MATCH(1,('827 Field Register'!$B$5:$B$831=A62)*('827 Field Register'!$C$5:$C$831=B62),0)) -> #N/A
A64: Total controlled fields | D64: =SUM(D5:D62) -> 827 | E64: =SUM(E5:E62) -> 1

Sheet 37 Work Packages
A1: OPBOH™ 37 Controlled Work Packages
A2: Six stage-specific focus fields are defined for every work package
A4: WP Code | B4: Work Package | C4: First Field | D4: Last Field | E4: Field Count | F4: Control Status
A5: WP01 | B5: Strategic Inception and Project Mandate | C5: WP01-01 | D5: WP01-06 | E5: 6 | F5: Complete
A6: WP02 | B6: Site Identification and Opportunity Discovery | C6: WP02-01 | D6: WP02-06 | E6: 6 | F6: Complete
A7: WP03 | B7: Preliminary Site Screening | C7: WP03-01 | D7: WP03-06 | E7: 6 | F7: Complete
A8: WP04 | B8: Sponsor and Entity Readiness | C8: WP04-01 | D8: WP04-06 | E8: 6 | F8: Complete
A9: WP05 | B9: Land Security and Site Control | C9: WP05-01 | D9: WP05-06 | E9: 6 | F9: Complete
A10: WP06 | B10: Feasibility Studies and Market Demand | C10: WP06-01 | D10: WP06-06 | E10: 6 | F10: Complete
A11: WP07 | B11: Traffic, Access and Mobility Feasibility | C11: WP07-01 | D11: WP07-06 | E11: 6 | F11: Complete
A12: WP08 | B12: Bulk Services and Infrastructure Feasibility | C12: WP08-01 | D12: WP08-06 | E12: 6 | F12: Complete
A13: WP09 | B13: Environmental Screening and Scoping | C13: WP09-01 | D13: WP09-06 | E13: 6 | F13: Complete
A14: WP10 | B14: Land Use Rights and Zoning | C14: WP10-01 | D14: WP10-06 | E14: 6 | F14: Complete
A15: WP11 | B15: Environmental Authorisation - Estimated 10 Months | C15: WP11-01 | D15: WP11-06 | E15: 6 | F15: Complete
A16: WP12 | B16: Stakeholder Mapping and Public Participation | C16: WP12-01 | D16: WP12-06 | E16: 6 | F16: Complete
... A41: WP37 | B41: Sustainable Impact, Performance Monitoring and Future Expansion | C41: WP37-01 | D41: WP37-06 | E41: 6 | F41: Complete

Sheet Controlled Lists
A1: Controlled Lists and Implementation Conventions
A2: Use these values for validation, configuration and system implementation
A4: List | B4: Code / Value | C4: Controlled Meaning
A5: Required Indicator | B5: M | C5: Mandatory
A6: Required Indicator | B6: C | C6: Conditional when applicable
A7: Required Indicator | B7: O | C7: Optional / supporting
A8: Required Indicator | B8: M/C | C8: Mandatory when the applicable stage, component, jurisdiction or risk rule is activated
A10: Core Rule | B10: Value | C10: Implementation Requirement
A11: Field code | B11: Stable identifier | C11: Never reuse a retired code for a different meaning.
A12: Null / N/A | B12: Distinct states | C12: N/A requires an approved applicability rationale and, where material, evidence.
A13: Material field | B13: Source + owner + approval + audit ref | C13: Required when used in a score, model, gate, capital decision or external report.
A14: Historical record | B14: Effective-dated | C14: Retain critical records so historical opinions and gate certificates can be reproduced exactly.
A15: Evidence | B15: Accepted + current + traceable | C15: A response or elapsed date alone cannot authorise progression.
A16: Critical control | B16: Non-averageable | C16: A strong average cannot conceal a failed mandatory floor, fatal flaw or critical control.
A17: Closure | B17: Evidence verified | C17: Discussion alone cannot close a finding, action or condition.

Sheet Source & Control
A1: Source, Authority and Document Control
A2: Controlled provenance for the OPBOH 827-field register
A4: Control Attribute | B4: Controlled Value
A5: Framework | B5: OPBOH™ — Organisational and Project Bill of Health
A6: Document ID | B6: IPACGS-OPBOH-MOD-FLD-001
A7: Version | B7: 1.1
A8: Issue Date | B8: 2026-08-06
A9: Source File | B9: OPBOH_Full_Cycle_Assessment_Module_Field_Requirements_v1.1.docx
A10: Owner | B10: IPAC Governance Systems (Pty) Ltd
A11: Classification | B11: Confidential and Proprietary
A12: Explicit Fields | B12: 827
A13: Controlled Work Packages | B13: 37
A14: Source Questions | B14: 3700
A15: Architecture Basis | B15: IPAC Governance Systems SRS v2.1; AGA; S1-S21; Gate 0-Gate 10; 37 controlled work packages
A17: Authoritative Positioning | B17: Controlled Statement
A18: OPBOH remains the Organisational and Project Bill of Health framework. This register defines the full-cycle OPBOH assessment-pack and data-model fields mapped to the 37 controlled work packages. It interoperates with related IPAC frameworks and does not rename or replace the authoritative registry framework.
A23: Purpose | B23: Controlled Statement
A24: Define the complete minimum data capture, validation, multi-format file and photo upload, content analysis, evidence, workflow, scoring, decision and reporting fields required to determine project assurance across the full project lifecycle.
